[
  {
    "tipo": "Incendio",
    "fecha": "2026-04-22",
    "hora": "13:42",
    "lat": -13.78668,
    "lon": -76.17098
  },
  {
    "tipo": "Incendio",
    "fecha": "2026-04-22",
    "hora": "13:42",
    "lat": -13.92531,
    "lon": -75.86587
  },
  {
    "tipo": "Incendio",
    "fecha": "2026-04-22",
    "hora": "19:34",
    "lat": -6.33994,
    "lon": -71.25377
  },
  {
    "tipo": "Incendio",
    "fecha": "2026-04-22",
    "hora": "21:10",
    "lat": -7.40317,
    "lon": -79.42958
  },
  {
    "tipo": "Incendio",
    "fecha": "2026-04-22",
    "hora": "21:10",
    "lat": -7.39459,
    "lon": -79.43743
  },
  {
    "tipo": "Incendio",
    "fecha": "2026-04-23",
    "hora": "01:56",
    "lat": -6.12471,
    "lon": -78.88021
  },
  {
    "tipo": "Incendio",
    "fecha": "2026-04-23",
    "hora": "07:58",
    "lat": -17.49294,
    "lon": -71.35518
  },
  {
    "tipo": "Sismo",
    "fecha": "2026-04-21T16:18:55.418Z",
    "lugar": "24 km ESE of Laraos, Peru",
    "magnitud": "4.5",
    "lat": -12.425,
    "lon": -75.5727
  },
  {
    "tipo": "Sismo",
    "fecha": "2026-04-20T23:26:41.426Z",
    "lugar": "81 km SW of Paracas, Peru",
    "magnitud": "4.3",
    "lat": -14.4599,
    "lon": -76.708
  },
  {
    "tipo": "Sismo",
    "fecha": "2026-04-19T18:20:00.432Z",
    "lugar": "26 km SE of Palca, Peru",
    "magnitud": "4.5",
    "lat": -17.97,
    "lon": -69.8069
  },
  {
    "tipo": "Sismo",
    "fecha": "2026-04-18T23:56:47.822Z",
    "lugar": "34 km NNE of Pucallpa, Peru",
    "magnitud": "4.2",
    "lat": -8.0836,
    "lon": -74.4617
  },
  {
    "tipo": "Sismo",
    "fecha": "2026-04-17T03:54:28.374Z",
    "lugar": "81 km S of Pacocha, Peru",
    "magnitud": "4.2",
    "lat": -18.386,
    "lon": -71.314
  }
]